{"EASI501": {"color": "blue", "activities": {"EASI501_CM_TC_CM1": {"kind": "CM", "duration": 6, "teachers": [[1, ["Teacher_FLep"]]], "rooms": [[1, ["Room_amphi_1", "Room_amphi_2"]]], "after": {}, "students": "CM_TC", "min_start_slot": null, "max_start_slot": null}, "EASI501_CM_TC_CM2": {"kind": "CM", "duration": 6, "teachers": [[1, ["Teacher_FLep"]]], "rooms": [[1, ["Room_amphi_1", "Room_amphi_2"]]], "after": {"EASI501": {"EASI501_CM_TC_CM1": {"min_offset": 0}}}, "students": "CM_TC", "min_start_slot": null, "max_start_slot": null}, "EASI501_CM_TC_CM3": {"kind": "CM", "duration": 6, "teachers": [[1, ["Teacher_FLep"]]], "rooms": [[1, ["Room_amphi_1", "Room_amphi_2"]]], "after": {"EASI501": {"EASI501_CM_TC_CM2": {"min_offset": 0}}}, "students": "CM_TC", "min_start_slot": null, "max_start_slot": null}, "EASI501_TDA_TD1": {"kind": "TD", "duration": 6, "teachers": [[1, ["Teacher_Lau"]]], "rooms": [[1, ["TD_Room_1", "TD_Room_2", "TD_Room_3", "TD_Room_4", "TD_Room_5", "TD_Room_6"]]], "after": {"EASI501": {"EASI501_CM_TC_CM3": {"min_offset": 0}}}, "students": "TDA", "min_start_slot": null, "max_start_slot": null}, "EASI501_TDB_TD1": {"kind": "TD", "duration": 6, "teachers": [[1, ["Teacher_YY"]]], "rooms": [[1, ["TD_Room_1", "TD_Room_2", "TD_Room_3", "TD_Room_4", "TD_Room_5", "TD_Room_6"]]], "after": {"EASI501": {"EASI501_CM_TC_CM3": {"min_offset": 0}}}, "students": "TDB", "min_start_slot": null, "max_start_slot": null}, "EASI501_TDC_TD1": {"kind": "TD", "duration": 6, "teachers": [[1, ["Teacher_Seb"]]], "rooms": [[1, ["TD_Room_1", "TD_Room_2", "TD_Room_3", "TD_Room_4", "TD_Room_5", "TD_Room_6"]]], "after": {"EASI501": {"EASI501_CM_TC_CM3": {"min_offset": 0}}}, "students": "TDC", "min_start_slot": null, "max_start_slot": null}, "EASI501_TDD_TD1": {"kind": "TD", "duration": 6, "teachers": [[1, ["Teacher_Lau"]]], "rooms": [[1, ["TD_Room_1", "TD_Room_2", "TD_Room_3", "TD_Room_4", "TD_Room_5", "TD_Room_6"]]], "after": {"EASI501": {"EASI501_CM_TC_CM3": {"min_offset": 0}}}, "students": "TDD", "min_start_slot": null, "max_start_slot": null}, "EASI501_TDE_TD1": {"kind": "TD", "duration": 6, "teachers": [[1, ["Teacher_Lau"]]], "rooms": [[1, ["TD_Room_1", "TD_Room_2", "TD_Room_3", "TD_Room_4", "TD_Room_5", "TD_Room_6"]]], "after": {"EASI501": {"EASI501_CM_TC_CM3": {"min_offset": 0}}}, "students": "TDE", "min_start_slot": null, "max_start_slot": null}, "EASI501_TDG_TD1": {"kind": "TD", "duration": 6, "teachers": [[1, ["Teacher_YY"]]], "rooms": [[1, ["TD_Room_1", "TD_Room_2", "TD_Room_3", "TD_Room_4", "TD_Room_5", "TD_Room_6"]]], "after": {"EASI501": {"EASI501_CM_TC_CM3": {"min_offset": 0}}}, "students": "TDG", "min_start_slot": null, "max_start_slot": null}, "EASI501_CM_TC_CM4": {"kind": "CM", "duration": 6, "teachers": [[1, ["Teacher_FLep"]]], "rooms": [[1, ["Room_amphi_1", "Room_amphi_2"]]], "after": {"EASI501": {"EASI501_TDA_TD1": {"min_offset": 0}, "EASI501_TDB_TD1": {"min_offset": 0}, "EASI501_TDC_TD1": {"min_offset": 0}, "EASI501_TDD_TD1": {"min_offset": 0}, "EASI501_TDE_TD1": {"min_offset": 0}, "EASI501_TDG_TD1": {"min_offset": 0}}}, "students": "CM_TC", "min_start_slot": null, "max_start_slot": null}, "EASI501_TDA_TD2": {"kind": "TD", "duration": 6, "teachers": [[1, ["Teacher_Lau"]]], "rooms": [[1, ["TD_Room_1", "TD_Room_2", "TD_Room_3", "TD_Room_4", "TD_Room_5", "TD_Room_6"]]], "after": {"EASI501": {"EASI501_CM_TC_CM4": {"min_offset": 0}}}, "students": "TDA", "min_start_slot": null, "max_start_slot": null}, "EASI501_TDB_TD2": {"kind": "TD", "duration": 6, "teachers": [[1, ["Teacher_YY"]]], "rooms": [[1, ["TD_Room_1", "TD_Room_2", "TD_Room_3", "TD_Room_4", "TD_Room_5", "TD_Room_6"]]], "after": {"EASI501": {"EASI501_CM_TC_CM4": {"min_offset": 0}}}, "students": "TDB", "min_start_slot": null, "max_start_slot": null}, "EASI501_TDC_TD2": {"kind": "TD", "duration": 6, "teachers": [[1, ["Teacher_Seb"]]], "rooms": [[1, ["TD_Room_1", "TD_Room_2", "TD_Room_3", "TD_Room_4", "TD_Room_5", "TD_Room_6"]]], "after": {"EASI501": {"EASI501_CM_TC_CM4": {"min_offset": 0}}}, "students": "TDC", "min_start_slot": null, "max_start_slot": null}, "EASI501_TDD_TD2": {"kind": "TD", "duration": 6, "teachers": [[1, ["Teacher_Lau"]]], "rooms": [[1, ["TD_Room_1", "TD_Room_2", "TD_Room_3", "TD_Room_4", "TD_Room_5", "TD_Room_6"]]], "after": {"EASI501": {"EASI501_CM_TC_CM4": {"min_offset": 0}}}, "students": "TDD", "min_start_slot": null, "max_start_slot": null}, "EASI501_TDE_TD2": {"kind": "TD", "duration": 6, "teachers": [[1, ["Teacher_Lau"]]], "rooms": [[1, ["TD_Room_1", "TD_Room_2", "TD_Room_3", "TD_Room_4", "TD_Room_5", "TD_Room_6"]]], "after": {"EASI501": {"EASI501_CM_TC_CM4": {"min_offset": 0}}}, "students": "TDE", "min_start_slot": null, "max_start_slot": null}, "EASI501_TDG_TD2": {"kind": "TD", "duration": 6, "teachers": [[1, ["Teacher_YY"]]], "rooms": [[1, ["TD_Room_1", "TD_Room_2", "TD_Room_3", "TD_Room_4", "TD_Room_5", "TD_Room_6"]]], "after": {"EASI501": {"EASI501_CM_TC_CM4": {"min_offset": 0}}}, "students": "TDG", "min_start_slot": null, "max_start_slot": null}, "EASI501_CM_TC_CM5": {"kind": "CM", "duration": 6, "teachers": [[1, ["Teacher_FLep"]]], "rooms": [[1, ["Room_amphi_1", "Room_amphi_2"]]], "after": {"EASI501": {"EASI501_TDA_TD2": {"min_offset": 0}, "EASI501_TDB_TD2": {"min_offset": 0}, "EASI501_TDC_TD2": {"min_offset": 0}, "EASI501_TDD_TD2": {"min_offset": 0}, "EASI501_TDE_TD2": {"min_offset": 0}, "EASI501_TDG_TD2": {"min_offset": 0}}}, "students": "CM_TC", "min_start_slot": null, "max_start_slot": null}, "EASI501_TDA_TD3": {"kind": "TD", "duration": 6, "teachers": [[1, ["Teacher_Lau"]]], "rooms": [[1, ["TD_Room_1", "TD_Room_2", "TD_Room_3", "TD_Room_4", "TD_Room_5", "TD_Room_6"]]], "after": {"EASI501": {"EASI501_CM_TC_CM5": {"min_offset": 0}}}, "students": "TDA", "min_start_slot": null, "max_start_slot": null}, "EASI501_TDB_TD3": {"kind": "TD", "duration": 6, "teachers": [[1, ["Teacher_YY"]]], "rooms": [[1, ["TD_Room_1", "TD_Room_2", "TD_Room_3", "TD_Room_4", "TD_Room_5", "TD_Room_6"]]], "after": {"EASI501": {"EASI501_CM_TC_CM5": {"min_offset": 0}}}, "students": "TDB", "min_start_slot": null, "max_start_slot": null}, "EASI501_TDC_TD3": {"kind": "TD", "duration": 6, "teachers": [[1, ["Teacher_Seb"]]], "rooms": [[1, ["TD_Room_1", "TD_Room_2", "TD_Room_3", "TD_Room_4", "TD_Room_5", "TD_Room_6"]]], "after": {"EASI501": {"EASI501_CM_TC_CM5": {"min_offset": 0}}}, "students": "TDC", "min_start_slot": null, "max_start_slot": null}, "EASI501_TDD_TD3": {"kind": "TD", "duration": 6, "teachers": [[1, ["Teacher_Lau"]]], "rooms": [[1, ["TD_Room_1", "TD_Room_2", "TD_Room_3", "TD_Room_4", "TD_Room_5", "TD_Room_6"]]], "after": {"EASI501": {"EASI501_CM_TC_CM5": {"min_offset": 0}}}, "students": "TDD", "min_start_slot": null, "max_start_slot": null}, "EASI501_TDE_TD3": {"kind": "TD", "duration": 6, "teachers": [[1, ["Teacher_Lau"]]], "rooms": [[1, ["TD_Room_1", "TD_Room_2", "TD_Room_3", "TD_Room_4", "TD_Room_5", "TD_Room_6"]]], "after": {"EASI501": {"EASI501_CM_TC_CM5": {"min_offset": 0}}}, "students": "TDE", "min_start_slot": null, "max_start_slot": null}, "EASI501_TDG_TD3": {"kind": "TD", "duration": 6, "teachers": [[1, ["Teacher_YY"]]], "rooms": [[1, ["TD_Room_1", "TD_Room_2", "TD_Room_3", "TD_Room_4", "TD_Room_5", "TD_Room_6"]]], "after": {"EASI501": {"EASI501_CM_TC_CM5": {"min_offset": 0}}}, "students": "TDG", "min_start_slot": null, "max_start_slot": null}, "EASI501_CM_TC_CM6": {"kind": "CM", "duration": 6, "teachers": [[1, ["Teacher_FLep"]]], "rooms": [[1, ["Room_amphi_1", "Room_amphi_2"]]], "after": {"EASI501": {"EASI501_TDA_TD3": {"min_offset": 0}, "EASI501_TDB_TD3": {"min_offset": 0}, "EASI501_TDC_TD3": {"min_offset": 0}, "EASI501_TDD_TD3": {"min_offset": 0}, "EASI501_TDE_TD3": {"min_offset": 0}, "EASI501_TDG_TD3": {"min_offset": 0}}}, "students": "CM_TC", "min_start_slot": null, "max_start_slot": null}, "EASI501_TDA_TD4": {"kind": "TD", "duration": 6, "teachers": [[1, ["Teacher_Lau"]]], "rooms": [[1, ["TD_Room_1", "TD_Room_2", "TD_Room_3", "TD_Room_4", "TD_Room_5", "TD_Room_6"]]], "after": {"EASI501": {"EASI501_CM_TC_CM6": {"min_offset": 0}}}, "students": "TDA", "min_start_slot": null, "max_start_slot": null}, "EASI501_TDB_TD4": {"kind": "TD", "duration": 6, "teachers": [[1, ["Teacher_YY"]]], "rooms": [[1, ["TD_Room_1", "TD_Room_2", "TD_Room_3", "TD_Room_4", "TD_Room_5", "TD_Room_6"]]], "after": {"EASI501": {"EASI501_CM_TC_CM6": {"min_offset": 0}}}, "students": "TDB", "min_start_slot": null, "max_start_slot": null}, "EASI501_TDC_TD4": {"kind": "TD", "duration": 6, "teachers": [[1, ["Teacher_Seb"]]], "rooms": [[1, ["TD_Room_1", "TD_Room_2", "TD_Room_3", "TD_Room_4", "TD_Room_5", "TD_Room_6"]]], "after": {"EASI501": {"EASI501_CM_TC_CM6": {"min_offset": 0}}}, "students": "TDC", "min_start_slot": null, "max_start_slot": null}, "EASI501_TDD_TD4": {"kind": "TD", "duration": 6, "teachers": [[1, ["Teacher_Lau"]]], "rooms": [[1, ["TD_Room_1", "TD_Room_2", "TD_Room_3", "TD_Room_4", "TD_Room_5", "TD_Room_6"]]], "after": {"EASI501": {"EASI501_CM_TC_CM6": {"min_offset": 0}}}, "students": "TDD", "min_start_slot": null, "max_start_slot": null}, "EASI501_TDE_TD4": {"kind": "TD", "duration": 6, "teachers": [[1, ["Teacher_Lau"]]], "rooms": [[1, ["TD_Room_1", "TD_Room_2", "TD_Room_3", "TD_Room_4", "TD_Room_5", "TD_Room_6"]]], "after": {"EASI501": {"EASI501_CM_TC_CM6": {"min_offset": 0}}}, "students": "TDE", "min_start_slot": null, "max_start_slot": null}, "EASI501_TDG_TD4": {"kind": "TD", "duration": 6, "teachers": [[1, ["Teacher_YY"]]], "rooms": [[1, ["TD_Room_1", "TD_Room_2", "TD_Room_3", "TD_Room_4", "TD_Room_5", "TD_Room_6"]]], "after": {"EASI501": {"EASI501_CM_TC_CM6": {"min_offset": 0}}}, "students": "TDG", "min_start_slot": null, "max_start_slot": null}, "EASI501_CM_TC_CM7": {"kind": "CM", "duration": 6, "teachers": [[1, ["Teacher_FLep"]]], "rooms": [[1, ["Room_amphi_1", "Room_amphi_2"]]], "after": {"EASI501": {"EASI501_TDA_TD4": {"min_offset": 0}, "EASI501_TDB_TD4": {"min_offset": 0}, "EASI501_TDC_TD4": {"min_offset": 0}, "EASI501_TDD_TD4": {"min_offset": 0}, "EASI501_TDE_TD4": {"min_offset": 0}, "EASI501_TDG_TD4": {"min_offset": 0}}}, "students": "CM_TC", "min_start_slot": null, "max_start_slot": null}, "EASI501_TDA_TD5": {"kind": "TD", "duration": 6, "teachers": [[1, ["Teacher_Lau"]]], "rooms": [[1, ["TD_Room_1", "TD_Room_2", "TD_Room_3", "TD_Room_4", "TD_Room_5", "TD_Room_6"]]], "after": {"EASI501": {"EASI501_CM_TC_CM7": {"min_offset": 0}}}, "students": "TDA", "min_start_slot": null, "max_start_slot": null}, "EASI501_TDB_TD5": {"kind": "TD", "duration": 6, "teachers": [[1, ["Teacher_YY"]]], "rooms": [[1, ["TD_Room_1", "TD_Room_2", "TD_Room_3", "TD_Room_4", "TD_Room_5", "TD_Room_6"]]], "after": {"EASI501": {"EASI501_CM_TC_CM7": {"min_offset": 0}}}, "students": "TDB", "min_start_slot": null, "max_start_slot": null}, "EASI501_TDC_TD5": {"kind": "TD", "duration": 6, "teachers": [[1, ["Teacher_Seb"]]], "rooms": [[1, ["TD_Room_1", "TD_Room_2", "TD_Room_3", "TD_Room_4", "TD_Room_5", "TD_Room_6"]]], "after": {"EASI501": {"EASI501_CM_TC_CM7": {"min_offset": 0}}}, "students": "TDC", "min_start_slot": null, "max_start_slot": null}, "EASI501_TDD_TD5": {"kind": "TD", "duration": 6, "teachers": [[1, ["Teacher_Lau"]]], "rooms": [[1, ["TD_Room_1", "TD_Room_2", "TD_Room_3", "TD_Room_4", "TD_Room_5", "TD_Room_6"]]], "after": {"EASI501": {"EASI501_CM_TC_CM7": {"min_offset": 0}}}, "students": "TDD", "min_start_slot": null, "max_start_slot": null}, "EASI501_TDE_TD5": {"kind": "TD", "duration": 6, "teachers": [[1, ["Teacher_Lau"]]], "rooms": [[1, ["TD_Room_1", "TD_Room_2", "TD_Room_3", "TD_Room_4", "TD_Room_5", "TD_Room_6"]]], "after": {"EASI501": {"EASI501_CM_TC_CM7": {"min_offset": 0}}}, "students": "TDE", "min_start_slot": null, "max_start_slot": null}, "EASI501_TDG_TD5": {"kind": "TD", "duration": 6, "teachers": [[1, ["Teacher_YY"]]], "rooms": [[1, ["TD_Room_1", "TD_Room_2", "TD_Room_3", "TD_Room_4", "TD_Room_5", "TD_Room_6"]]], "after": {"EASI501": {"EASI501_CM_TC_CM7": {"min_offset": 0}}}, "students": "TDG", "min_start_slot": null, "max_start_slot": null}, "EASI501_CM_TC_CC1": {"kind": "EX", "duration": 1, "teachers": [[1, ["Teacher_Flep"]]], "rooms": [[2, ["Room_amphi_1", "Room_amphi_2"]]], "after": {"EASI501": {"EASI501_TDA_TD5": {"min_offset": 0}, "EASI501_TDB_TD5": {"min_offset": 0}, "EASI501_TDC_TD5": {"min_offset": 0}, "EASI501_TDD_TD5": {"min_offset": 0}, "EASI501_TDE_TD5": {"min_offset": 0}, "EASI501_TDG_TD5": {"min_offset": 0}}}, "students": "CM_TC", "min_start_slot": null, "max_start_slot": null}, "EASI501_TDA_TD6": {"kind": "TD", "duration": 6, "teachers": [[1, ["Teacher_Lau"]]], "rooms": [[1, ["TD_Room_1", "TD_Room_2", "TD_Room_3", "TD_Room_4", "TD_Room_5", "TD_Room_6"]]], "after": {"EASI501": {"EASI501_CM_TC_CC1": {"min_offset": 0}}}, "students": "TDA", "min_start_slot": null, "max_start_slot": null}, "EASI501_TDB_TD6": {"kind": "TD", "duration": 6, "teachers": [[1, ["Teacher_YY"]]], "rooms": [[1, ["TD_Room_1", "TD_Room_2", "TD_Room_3", "TD_Room_4", "TD_Room_5", "TD_Room_6"]]], "after": {"EASI501": {"EASI501_CM_TC_CC1": {"min_offset": 0}}}, "students": "TDB", "min_start_slot": null, "max_start_slot": null}, "EASI501_TDC_TD6": {"kind": "TD", "duration": 6, "teachers": [[1, ["Teacher_Seb"]]], "rooms": [[1, ["TD_Room_1", "TD_Room_2", "TD_Room_3", "TD_Room_4", "TD_Room_5", "TD_Room_6"]]], "after": {"EASI501": {"EASI501_CM_TC_CC1": {"min_offset": 0}}}, "students": "TDC", "min_start_slot": null, "max_start_slot": null}, "EASI501_TDD_TD6": {"kind": "TD", "duration": 6, "teachers": [[1, ["Teacher_Lau"]]], "rooms": [[1, ["TD_Room_1", "TD_Room_2", "TD_Room_3", "TD_Room_4", "TD_Room_5", "TD_Room_6"]]], "after": {"EASI501": {"EASI501_CM_TC_CC1": {"min_offset": 0}}}, "students": "TDD", "min_start_slot": null, "max_start_slot": null}, "EASI501_TDE_TD6": {"kind": "TD", "duration": 6, "teachers": [[1, ["Teacher_Lau"]]], "rooms": [[1, ["TD_Room_1", "TD_Room_2", "TD_Room_3", "TD_Room_4", "TD_Room_5", "TD_Room_6"]]], "after": {"EASI501": {"EASI501_CM_TC_CC1": {"min_offset": 0}}}, "students": "TDE", "min_start_slot": null, "max_start_slot": null}, "EASI501_TDG_TD6": {"kind": "TD", "duration": 6, "teachers": [[1, ["Teacher_YY"]]], "rooms": [[1, ["TD_Room_1", "TD_Room_2", "TD_Room_3", "TD_Room_4", "TD_Room_5", "TD_Room_6"]]], "after": {"EASI501": {"EASI501_CM_TC_CC1": {"min_offset": 0}}}, "students": "TDG", "min_start_slot": null, "max_start_slot": null}, "EASI501_TDA_TD7": {"kind": "TD", "duration": 6, "teachers": [[1, ["Teacher_Lau"]]], "rooms": [[1, ["TD_Room_1", "TD_Room_2", "TD_Room_3", "TD_Room_4", "TD_Room_5", "TD_Room_6"]]], "after": {"EASI501": {"EASI501_TDA_TD6": {"min_offset": 0}, "EASI501_TDB_TD6": {"min_offset": 0}, "EASI501_TDC_TD6": {"min_offset": 0}, "EASI501_TDD_TD6": {"min_offset": 0}, "EASI501_TDE_TD6": {"min_offset": 0}, "EASI501_TDG_TD6": {"min_offset": 0}}}, "students": "TDA", "min_start_slot": null, "max_start_slot": null}, "EASI501_TDB_TD7": {"kind": "TD", "duration": 6, "teachers": [[1, ["Teacher_YY"]]], "rooms": [[1, ["TD_Room_1", "TD_Room_2", "TD_Room_3", "TD_Room_4", "TD_Room_5", "TD_Room_6"]]], "after": {"EASI501": {"EASI501_TDA_TD6": {"min_offset": 0}, "EASI501_TDB_TD6": {"min_offset": 0}, "EASI501_TDC_TD6": {"min_offset": 0}, "EASI501_TDD_TD6": {"min_offset": 0}, "EASI501_TDE_TD6": {"min_offset": 0}, "EASI501_TDG_TD6": {"min_offset": 0}}}, "students": "TDB", "min_start_slot": null, "max_start_slot": null}, "EASI501_TDC_TD7": {"kind": "TD", "duration": 6, "teachers": [[1, ["Teacher_Seb"]]], "rooms": [[1, ["TD_Room_1", "TD_Room_2", "TD_Room_3", "TD_Room_4", "TD_Room_5", "TD_Room_6"]]], "after": {"EASI501": {"EASI501_TDA_TD6": {"min_offset": 0}, "EASI501_TDB_TD6": {"min_offset": 0}, "EASI501_TDC_TD6": {"min_offset": 0}, "EASI501_TDD_TD6": {"min_offset": 0}, "EASI501_TDE_TD6": {"min_offset": 0}, "EASI501_TDG_TD6": {"min_offset": 0}}}, "students": "TDC", "min_start_slot": null, "max_start_slot": null}, "EASI501_TDD_TD7": {"kind": "TD", "duration": 6, "teachers": [[1, ["Teacher_Lau"]]], "rooms": [[1, ["TD_Room_1", "TD_Room_2", "TD_Room_3", "TD_Room_4", "TD_Room_5", "TD_Room_6"]]], "after": {"EASI501": {"EASI501_TDA_TD6": {"min_offset": 0}, "EASI501_TDB_TD6": {"min_offset": 0}, "EASI501_TDC_TD6": {"min_offset": 0}, "EASI501_TDD_TD6": {"min_offset": 0}, "EASI501_TDE_TD6": {"min_offset": 0}, "EASI501_TDG_TD6": {"min_offset": 0}}}, "students": "TDD", "min_start_slot": null, "max_start_slot": null}, "EASI501_TDE_TD7": {"kind": "TD", "duration": 6, "teachers": [[1, ["Teacher_Lau"]]], "rooms": [[1, ["TD_Room_1", "TD_Room_2", "TD_Room_3", "TD_Room_4", "TD_Room_5", "TD_Room_6"]]], "after": {"EASI501": {"EASI501_TDA_TD6": {"min_offset": 0}, "EASI501_TDB_TD6": {"min_offset": 0}, "EASI501_TDC_TD6": {"min_offset": 0}, "EASI501_TDD_TD6": {"min_offset": 0}, "EASI501_TDE_TD6": {"min_offset": 0}, "EASI501_TDG_TD6": {"min_offset": 0}}}, "students": "TDE", "min_start_slot": null, "max_start_slot": null}, "EASI501_TDG_TD7": {"kind": "TD", "duration": 6, "teachers": [[1, ["Teacher_YY"]]], "rooms": [[1, ["TD_Room_1", "TD_Room_2", "TD_Room_3", "TD_Room_4", "TD_Room_5", "TD_Room_6"]]], "after": {"EASI501": {"EASI501_TDA_TD6": {"min_offset": 0}, "EASI501_TDB_TD6": {"min_offset": 0}, "EASI501_TDC_TD6": {"min_offset": 0}, "EASI501_TDD_TD6": {"min_offset": 0}, "EASI501_TDE_TD6": {"min_offset": 0}, "EASI501_TDG_TD6": {"min_offset": 0}}}, "students": "TDG", "min_start_slot": null, "max_start_slot": null}, "EASI501_TPA1_TP1": {"kind": "TP", "duration": 16, "teachers": [[1, ["Teacher_FLep"]]], "rooms": [[1, ["C121"]]], "after": {"EASI501": {"EASI501_TDA_TD3": {"min_offset": 0}, "EASI501_TDB_TD3": {"min_offset": 0}, "EASI501_TDC_TD3": {"min_offset": 0}, "EASI501_TDD_TD3": {"min_offset": 0}, "EASI501_TDE_TD3": {"min_offset": 0}, "EASI501_TDG_TD3": {"min_offset": 0}}}, "students": "TPA1", "min_start_slot": null, "max_start_slot": null}, "EASI501_TPA2_TP1": {"kind": "TP", "duration": 16, "teachers": [[1, ["Teacher_FLep"]]], "rooms": [[1, ["C121"]]], "after": {"EASI501": {"EASI501_TDA_TD3": {"min_offset": 0}, "EASI501_TDB_TD3": {"min_offset": 0}, "EASI501_TDC_TD3": {"min_offset": 0}, "EASI501_TDD_TD3": {"min_offset": 0}, "EASI501_TDE_TD3": {"min_offset": 0}, "EASI501_TDG_TD3": {"min_offset": 0}}}, "students": "TPA2", "min_start_slot": null, "max_start_slot": null}, "EASI501_TPB1_TP1": {"kind": "TP", "duration": 16, "teachers": [[1, ["Teacher_CHern"]]], "rooms": [[1, ["C121"]]], "after": {"EASI501": {"EASI501_TDA_TD3": {"min_offset": 0}, "EASI501_TDB_TD3": {"min_offset": 0}, "EASI501_TDC_TD3": {"min_offset": 0}, "EASI501_TDD_TD3": {"min_offset": 0}, "EASI501_TDE_TD3": {"min_offset": 0}, "EASI501_TDG_TD3": {"min_offset": 0}}}, "students": "TPB1", "min_start_slot": null, "max_start_slot": null}, "EASI501_TPB2_TP1": {"kind": "TP", "duration": 16, "teachers": [[1, ["Teacher_LMarech"]]], "rooms": [[1, ["C121"]]], "after": {"EASI501": {"EASI501_TDA_TD3": {"min_offset": 0}, "EASI501_TDB_TD3": {"min_offset": 0}, "EASI501_TDC_TD3": {"min_offset": 0}, "EASI501_TDD_TD3": {"min_offset": 0}, "EASI501_TDE_TD3": {"min_offset": 0}, "EASI501_TDG_TD3": {"min_offset": 0}}}, "students": "TPB2", "min_start_slot": null, "max_start_slot": null}, "EASI501_TPC1_TP1": {"kind": "TP", "duration": 16, "teachers": [[1, ["Teacher_CHern"]]], "rooms": [[1, ["C121"]]], "after": {"EASI501": {"EASI501_TDA_TD3": {"min_offset": 0}, "EASI501_TDB_TD3": {"min_offset": 0}, "EASI501_TDC_TD3": {"min_offset": 0}, "EASI501_TDD_TD3": {"min_offset": 0}, "EASI501_TDE_TD3": {"min_offset": 0}, "EASI501_TDG_TD3": {"min_offset": 0}}}, "students": "TPC1", "min_start_slot": null, "max_start_slot": null}, "EASI501_TPC2_TP1": {"kind": "TP", "duration": 16, "teachers": [[1, ["Teacher_MPass"]]], "rooms": [[1, ["C121"]]], "after": {"EASI501": {"EASI501_TDA_TD3": {"min_offset": 0}, "EASI501_TDB_TD3": {"min_offset": 0}, "EASI501_TDC_TD3": {"min_offset": 0}, "EASI501_TDD_TD3": {"min_offset": 0}, "EASI501_TDE_TD3": {"min_offset": 0}, "EASI501_TDG_TD3": {"min_offset": 0}}}, "students": "TPC2", "min_start_slot": null, "max_start_slot": null}, "EASI501_TPD1_TP1": {"kind": "TP", "duration": 16, "teachers": [[1, ["Teacher_FLep"]]], "rooms": [[1, ["C121"]]], "after": {"EASI501": {"EASI501_TDA_TD3": {"min_offset": 0}, "EASI501_TDB_TD3": {"min_offset": 0}, "EASI501_TDC_TD3": {"min_offset": 0}, "EASI501_TDD_TD3": {"min_offset": 0}, "EASI501_TDE_TD3": {"min_offset": 0}, "EASI501_TDG_TD3": {"min_offset": 0}}}, "students": "TPD1", "min_start_slot": null, "max_start_slot": null}, "EASI501_TPD2_TP1": {"kind": "TP", "duration": 16, "teachers": [[1, ["Teacher_MPass"]]], "rooms": [[1, ["C121"]]], "after": {"EASI501": {"EASI501_TDA_TD3": {"min_offset": 0}, "EASI501_TDB_TD3": {"min_offset": 0}, "EASI501_TDC_TD3": {"min_offset": 0}, "EASI501_TDD_TD3": {"min_offset": 0}, "EASI501_TDE_TD3": {"min_offset": 0}, "EASI501_TDG_TD3": {"min_offset": 0}}}, "students": "TPD2", "min_start_slot": null, "max_start_slot": null}, "EASI501_TPE1_TP1": {"kind": "TP", "duration": 16, "teachers": [[1, ["Teacher_MPass"]]], "rooms": [[1, ["C121"]]], "after": {"EASI501": {"EASI501_TDA_TD3": {"min_offset": 0}, "EASI501_TDB_TD3": {"min_offset": 0}, "EASI501_TDC_TD3": {"min_offset": 0}, "EASI501_TDD_TD3": {"min_offset": 0}, "EASI501_TDE_TD3": {"min_offset": 0}, "EASI501_TDG_TD3": {"min_offset": 0}}}, "students": "TPE1", "min_start_slot": null, "max_start_slot": null}, "EASI501_TPE2_TP1": {"kind": "TP", "duration": 16, "teachers": [[1, ["Teacher_FLep"]]], "rooms": [[1, ["C121"]]], "after": {"EASI501": {"EASI501_TDA_TD3": {"min_offset": 0}, "EASI501_TDB_TD3": {"min_offset": 0}, "EASI501_TDC_TD3": {"min_offset": 0}, "EASI501_TDD_TD3": {"min_offset": 0}, "EASI501_TDE_TD3": {"min_offset": 0}, "EASI501_TDG_TD3": {"min_offset": 0}}}, "students": "TPE2", "min_start_slot": null, "max_start_slot": null}, "EASI501_TPG1_TP1": {"kind": "TP", "duration": 16, "teachers": [[1, ["Teacher_FLep"]]], "rooms": [[1, ["C121"]]], "after": {"EASI501": {"EASI501_TDA_TD3": {"min_offset": 0}, "EASI501_TDB_TD3": {"min_offset": 0}, "EASI501_TDC_TD3": {"min_offset": 0}, "EASI501_TDD_TD3": {"min_offset": 0}, "EASI501_TDE_TD3": {"min_offset": 0}, "EASI501_TDG_TD3": {"min_offset": 0}}}, "students": "TPG1", "min_start_slot": null, "max_start_slot": null}, "EASI501_TPG2_TP1": {"kind": "TP", "duration": 16, "teachers": [[1, ["Teacher_FLep"]]], "rooms": [[1, ["C121"]]], "after": {"EASI501": {"EASI501_TDA_TD3": {"min_offset": 0}, "EASI501_TDB_TD3": {"min_offset": 0}, "EASI501_TDC_TD3": {"min_offset": 0}, "EASI501_TDD_TD3": {"min_offset": 0}, "EASI501_TDE_TD3": {"min_offset": 0}, "EASI501_TDG_TD3": {"min_offset": 0}}}, "students": "TPG2", "min_start_slot": null, "max_start_slot": null}, "EASI501_TPA1_TP2": {"kind": "TP", "duration": 16, "teachers": [[1, ["Teacher_FLep"]]], "rooms": [[1, ["A202"]]], "after": {"EASI501": {"EASI501_TPA1_TP1": {"min_offset": 0}, "EASI501_TPA2_TP1": {"min_offset": 0}, "EASI501_TPB1_TP1": {"min_offset": 0}, "EASI501_TPB2_TP1": {"min_offset": 0}, "EASI501_TPC1_TP1": {"min_offset": 0}, "EASI501_TPC2_TP1": {"min_offset": 0}, "EASI501_TPD1_TP1": {"min_offset": 0}, "EASI501_TPD2_TP1": {"min_offset": 0}, "EASI501_TPE1_TP1": {"min_offset": 0}, "EASI501_TPE2_TP1": {"min_offset": 0}, "EASI501_TPG1_TP1": {"min_offset": 0}, "EASI501_TPG2_TP1": {"min_offset": 0}}}, "students": "TPA1", "min_start_slot": null, "max_start_slot": null}, "EASI501_TPA2_TP2": {"kind": "TP", "duration": 16, "teachers": [[1, ["Teacher_FLep"]]], "rooms": [[1, ["A202"]]], "after": {"EASI501": {"EASI501_TPA1_TP1": {"min_offset": 0}, "EASI501_TPA2_TP1": {"min_offset": 0}, "EASI501_TPB1_TP1": {"min_offset": 0}, "EASI501_TPB2_TP1": {"min_offset": 0}, "EASI501_TPC1_TP1": {"min_offset": 0}, "EASI501_TPC2_TP1": {"min_offset": 0}, "EASI501_TPD1_TP1": {"min_offset": 0}, "EASI501_TPD2_TP1": {"min_offset": 0}, "EASI501_TPE1_TP1": {"min_offset": 0}, "EASI501_TPE2_TP1": {"min_offset": 0}, "EASI501_TPG1_TP1": {"min_offset": 0}, "EASI501_TPG2_TP1": {"min_offset": 0}}}, "students": "TPA2", "min_start_slot": null, "max_start_slot": null}, "EASI501_TPB1_TP2": {"kind": "TP", "duration": 16, "teachers": [[1, ["Teacher_CHern"]]], "rooms": [[1, ["A202"]]], "after": {"EASI501": {"EASI501_TPA1_TP1": {"min_offset": 0}, "EASI501_TPA2_TP1": {"min_offset": 0}, "EASI501_TPB1_TP1": {"min_offset": 0}, "EASI501_TPB2_TP1": {"min_offset": 0}, "EASI501_TPC1_TP1": {"min_offset": 0}, "EASI501_TPC2_TP1": {"min_offset": 0}, "EASI501_TPD1_TP1": {"min_offset": 0}, "EASI501_TPD2_TP1": {"min_offset": 0}, "EASI501_TPE1_TP1": {"min_offset": 0}, "EASI501_TPE2_TP1": {"min_offset": 0}, "EASI501_TPG1_TP1": {"min_offset": 0}, "EASI501_TPG2_TP1": {"min_offset": 0}}}, "students": "TPB1", "min_start_slot": null, "max_start_slot": null}, "EASI501_TPB2_TP2": {"kind": "TP", "duration": 16, "teachers": [[1, ["Teacher_LMarech"]]], "rooms": [[1, ["A202"]]], "after": {"EASI501": {"EASI501_TPA1_TP1": {"min_offset": 0}, "EASI501_TPA2_TP1": {"min_offset": 0}, "EASI501_TPB1_TP1": {"min_offset": 0}, "EASI501_TPB2_TP1": {"min_offset": 0}, "EASI501_TPC1_TP1": {"min_offset": 0}, "EASI501_TPC2_TP1": {"min_offset": 0}, "EASI501_TPD1_TP1": {"min_offset": 0}, "EASI501_TPD2_TP1": {"min_offset": 0}, "EASI501_TPE1_TP1": {"min_offset": 0}, "EASI501_TPE2_TP1": {"min_offset": 0}, "EASI501_TPG1_TP1": {"min_offset": 0}, "EASI501_TPG2_TP1": {"min_offset": 0}}}, "students": "TPB2", "min_start_slot": null, "max_start_slot": null}, "EASI501_TPC1_TP2": {"kind": "TP", "duration": 16, "teachers": [[1, ["Teacher_CHern"]]], "rooms": [[1, ["A202"]]], "after": {"EASI501": {"EASI501_TPA1_TP1": {"min_offset": 0}, "EASI501_TPA2_TP1": {"min_offset": 0}, "EASI501_TPB1_TP1": {"min_offset": 0}, "EASI501_TPB2_TP1": {"min_offset": 0}, "EASI501_TPC1_TP1": {"min_offset": 0}, "EASI501_TPC2_TP1": {"min_offset": 0}, "EASI501_TPD1_TP1": {"min_offset": 0}, "EASI501_TPD2_TP1": {"min_offset": 0}, "EASI501_TPE1_TP1": {"min_offset": 0}, "EASI501_TPE2_TP1": {"min_offset": 0}, "EASI501_TPG1_TP1": {"min_offset": 0}, "EASI501_TPG2_TP1": {"min_offset": 0}}}, "students": "TPC1", "min_start_slot": null, "max_start_slot": null}, "EASI501_TPC2_TP2": {"kind": "TP", "duration": 16, "teachers": [[1, ["Teacher_MPass"]]], "rooms": [[1, ["A202"]]], "after": {"EASI501": {"EASI501_TPA1_TP1": {"min_offset": 0}, "EASI501_TPA2_TP1": {"min_offset": 0}, "EASI501_TPB1_TP1": {"min_offset": 0}, "EASI501_TPB2_TP1": {"min_offset": 0}, "EASI501_TPC1_TP1": {"min_offset": 0}, "EASI501_TPC2_TP1": {"min_offset": 0}, "EASI501_TPD1_TP1": {"min_offset": 0}, "EASI501_TPD2_TP1": {"min_offset": 0}, "EASI501_TPE1_TP1": {"min_offset": 0}, "EASI501_TPE2_TP1": {"min_offset": 0}, "EASI501_TPG1_TP1": {"min_offset": 0}, "EASI501_TPG2_TP1": {"min_offset": 0}}}, "students": "TPC2", "min_start_slot": null, "max_start_slot": null}, "EASI501_TPD1_TP2": {"kind": "TP", "duration": 16, "teachers": [[1, ["Teacher_FLep"]]], "rooms": [[1, ["A202"]]], "after": {"EASI501": {"EASI501_TPA1_TP1": {"min_offset": 0}, "EASI501_TPA2_TP1": {"min_offset": 0}, "EASI501_TPB1_TP1": {"min_offset": 0}, "EASI501_TPB2_TP1": {"min_offset": 0}, "EASI501_TPC1_TP1": {"min_offset": 0}, "EASI501_TPC2_TP1": {"min_offset": 0}, "EASI501_TPD1_TP1": {"min_offset": 0}, "EASI501_TPD2_TP1": {"min_offset": 0}, "EASI501_TPE1_TP1": {"min_offset": 0}, "EASI501_TPE2_TP1": {"min_offset": 0}, "EASI501_TPG1_TP1": {"min_offset": 0}, "EASI501_TPG2_TP1": {"min_offset": 0}}}, "students": "TPD1", "min_start_slot": null, "max_start_slot": null}, "EASI501_TPD2_TP2": {"kind": "TP", "duration": 16, "teachers": [[1, ["Teacher_MPass"]]], "rooms": [[1, ["A202"]]], "after": {"EASI501": {"EASI501_TPA1_TP1": {"min_offset": 0}, "EASI501_TPA2_TP1": {"min_offset": 0}, "EASI501_TPB1_TP1": {"min_offset": 0}, "EASI501_TPB2_TP1": {"min_offset": 0}, "EASI501_TPC1_TP1": {"min_offset": 0}, "EASI501_TPC2_TP1": {"min_offset": 0}, "EASI501_TPD1_TP1": {"min_offset": 0}, "EASI501_TPD2_TP1": {"min_offset": 0}, "EASI501_TPE1_TP1": {"min_offset": 0}, "EASI501_TPE2_TP1": {"min_offset": 0}, "EASI501_TPG1_TP1": {"min_offset": 0}, "EASI501_TPG2_TP1": {"min_offset": 0}}}, "students": "TPD2", "min_start_slot": null, "max_start_slot": null}, "EASI501_TPE1_TP2": {"kind": "TP", "duration": 16, "teachers": [[1, ["Teacher_MPass"]]], "rooms": [[1, ["A202"]]], "after": {"EASI501": {"EASI501_TPA1_TP1": {"min_offset": 0}, "EASI501_TPA2_TP1": {"min_offset": 0}, "EASI501_TPB1_TP1": {"min_offset": 0}, "EASI501_TPB2_TP1": {"min_offset": 0}, "EASI501_TPC1_TP1": {"min_offset": 0}, "EASI501_TPC2_TP1": {"min_offset": 0}, "EASI501_TPD1_TP1": {"min_offset": 0}, "EASI501_TPD2_TP1": {"min_offset": 0}, "EASI501_TPE1_TP1": {"min_offset": 0}, "EASI501_TPE2_TP1": {"min_offset": 0}, "EASI501_TPG1_TP1": {"min_offset": 0}, "EASI501_TPG2_TP1": {"min_offset": 0}}}, "students": "TPE1", "min_start_slot": null, "max_start_slot": null}, "EASI501_TPE2_TP2": {"kind": "TP", "duration": 16, "teachers": [[1, ["Teacher_FLep"]]], "rooms": [[1, ["A202"]]], "after": {"EASI501": {"EASI501_TPA1_TP1": {"min_offset": 0}, "EASI501_TPA2_TP1": {"min_offset": 0}, "EASI501_TPB1_TP1": {"min_offset": 0}, "EASI501_TPB2_TP1": {"min_offset": 0}, "EASI501_TPC1_TP1": {"min_offset": 0}, "EASI501_TPC2_TP1": {"min_offset": 0}, "EASI501_TPD1_TP1": {"min_offset": 0}, "EASI501_TPD2_TP1": {"min_offset": 0}, "EASI501_TPE1_TP1": {"min_offset": 0}, "EASI501_TPE2_TP1": {"min_offset": 0}, "EASI501_TPG1_TP1": {"min_offset": 0}, "EASI501_TPG2_TP1": {"min_offset": 0}}}, "students": "TPE2", "min_start_slot": null, "max_start_slot": null}, "EASI501_TPG1_TP2": {"kind": "TP", "duration": 16, "teachers": [[1, ["Teacher_FLep"]]], "rooms": [[1, ["A202"]]], "after": {"EASI501": {"EASI501_TPA1_TP1": {"min_offset": 0}, "EASI501_TPA2_TP1": {"min_offset": 0}, "EASI501_TPB1_TP1": {"min_offset": 0}, "EASI501_TPB2_TP1": {"min_offset": 0}, "EASI501_TPC1_TP1": {"min_offset": 0}, "EASI501_TPC2_TP1": {"min_offset": 0}, "EASI501_TPD1_TP1": {"min_offset": 0}, "EASI501_TPD2_TP1": {"min_offset": 0}, "EASI501_TPE1_TP1": {"min_offset": 0}, "EASI501_TPE2_TP1": {"min_offset": 0}, "EASI501_TPG1_TP1": {"min_offset": 0}, "EASI501_TPG2_TP1": {"min_offset": 0}}}, "students": "TPG1", "min_start_slot": null, "max_start_slot": null}, "EASI501_TPG2_TP2": {"kind": "TP", "duration": 16, "teachers": [[1, ["Teacher_FLep"]]], "rooms": [[1, ["A202"]]], "after": {"EASI501": {"EASI501_TPA1_TP1": {"min_offset": 0}, "EASI501_TPA2_TP1": {"min_offset": 0}, "EASI501_TPB1_TP1": {"min_offset": 0}, "EASI501_TPB2_TP1": {"min_offset": 0}, "EASI501_TPC1_TP1": {"min_offset": 0}, "EASI501_TPC2_TP1": {"min_offset": 0}, "EASI501_TPD1_TP1": {"min_offset": 0}, "EASI501_TPD2_TP1": {"min_offset": 0}, "EASI501_TPE1_TP1": {"min_offset": 0}, "EASI501_TPE2_TP1": {"min_offset": 0}, "EASI501_TPG1_TP1": {"min_offset": 0}, "EASI501_TPG2_TP1": {"min_offset": 0}}}, "students": "TPG2", "min_start_slot": null, "max_start_slot": null}, "EASI501_TPA1_TP3": {"kind": "TP", "duration": 16, "teachers": [[1, ["Teacher_FLep"]]], "rooms": [[1, ["A202"]]], "after": {"EASI501": {"EASI501_TPA1_TP2": {"min_offset": 0}, "EASI501_TPA2_TP2": {"min_offset": 0}, "EASI501_TPB1_TP2": {"min_offset": 0}, "EASI501_TPB2_TP2": {"min_offset": 0}, "EASI501_TPC1_TP2": {"min_offset": 0}, "EASI501_TPC2_TP2": {"min_offset": 0}, "EASI501_TPD1_TP2": {"min_offset": 0}, "EASI501_TPD2_TP2": {"min_offset": 0}, "EASI501_TPE1_TP2": {"min_offset": 0}, "EASI501_TPE2_TP2": {"min_offset": 0}, "EASI501_TPG1_TP2": {"min_offset": 0}, "EASI501_TPG2_TP2": {"min_offset": 0}}}, "students": "TPA1", "min_start_slot": null, "max_start_slot": null}, "EASI501_TPA2_TP3": {"kind": "TP", "duration": 16, "teachers": [[1, ["Teacher_FLep"]]], "rooms": [[1, ["A202"]]], "after": {"EASI501": {"EASI501_TPA1_TP2": {"min_offset": 0}, "EASI501_TPA2_TP2": {"min_offset": 0}, "EASI501_TPB1_TP2": {"min_offset": 0}, "EASI501_TPB2_TP2": {"min_offset": 0}, "EASI501_TPC1_TP2": {"min_offset": 0}, "EASI501_TPC2_TP2": {"min_offset": 0}, "EASI501_TPD1_TP2": {"min_offset": 0}, "EASI501_TPD2_TP2": {"min_offset": 0}, "EASI501_TPE1_TP2": {"min_offset": 0}, "EASI501_TPE2_TP2": {"min_offset": 0}, "EASI501_TPG1_TP2": {"min_offset": 0}, "EASI501_TPG2_TP2": {"min_offset": 0}}}, "students": "TPA2", "min_start_slot": null, "max_start_slot": null}, "EASI501_TPB1_TP3": {"kind": "TP", "duration": 16, "teachers": [[1, ["Teacher_CHern"]]], "rooms": [[1, ["A202"]]], "after": {"EASI501": {"EASI501_TPA1_TP2": {"min_offset": 0}, "EASI501_TPA2_TP2": {"min_offset": 0}, "EASI501_TPB1_TP2": {"min_offset": 0}, "EASI501_TPB2_TP2": {"min_offset": 0}, "EASI501_TPC1_TP2": {"min_offset": 0}, "EASI501_TPC2_TP2": {"min_offset": 0}, "EASI501_TPD1_TP2": {"min_offset": 0}, "EASI501_TPD2_TP2": {"min_offset": 0}, "EASI501_TPE1_TP2": {"min_offset": 0}, "EASI501_TPE2_TP2": {"min_offset": 0}, "EASI501_TPG1_TP2": {"min_offset": 0}, "EASI501_TPG2_TP2": {"min_offset": 0}}}, "students": "TPB1", "min_start_slot": null, "max_start_slot": null}, "EASI501_TPB2_TP3": {"kind": "TP", "duration": 16, "teachers": [[1, ["Teacher_LMarech"]]], "rooms": [[1, ["A202"]]], "after": {"EASI501": {"EASI501_TPA1_TP2": {"min_offset": 0}, "EASI501_TPA2_TP2": {"min_offset": 0}, "EASI501_TPB1_TP2": {"min_offset": 0}, "EASI501_TPB2_TP2": {"min_offset": 0}, "EASI501_TPC1_TP2": {"min_offset": 0}, "EASI501_TPC2_TP2": {"min_offset": 0}, "EASI501_TPD1_TP2": {"min_offset": 0}, "EASI501_TPD2_TP2": {"min_offset": 0}, "EASI501_TPE1_TP2": {"min_offset": 0}, "EASI501_TPE2_TP2": {"min_offset": 0}, "EASI501_TPG1_TP2": {"min_offset": 0}, "EASI501_TPG2_TP2": {"min_offset": 0}}}, "students": "TPB2", "min_start_slot": null, "max_start_slot": null}, "EASI501_TPC1_TP3": {"kind": "TP", "duration": 16, "teachers": [[1, ["Teacher_CHern"]]], "rooms": [[1, ["A202"]]], "after": {"EASI501": {"EASI501_TPA1_TP2": {"min_offset": 0}, "EASI501_TPA2_TP2": {"min_offset": 0}, "EASI501_TPB1_TP2": {"min_offset": 0}, "EASI501_TPB2_TP2": {"min_offset": 0}, "EASI501_TPC1_TP2": {"min_offset": 0}, "EASI501_TPC2_TP2": {"min_offset": 0}, "EASI501_TPD1_TP2": {"min_offset": 0}, "EASI501_TPD2_TP2": {"min_offset": 0}, "EASI501_TPE1_TP2": {"min_offset": 0}, "EASI501_TPE2_TP2": {"min_offset": 0}, "EASI501_TPG1_TP2": {"min_offset": 0}, "EASI501_TPG2_TP2": {"min_offset": 0}}}, "students": "TPC1", "min_start_slot": null, "max_start_slot": null}, "EASI501_TPC2_TP3": {"kind": "TP", "duration": 16, "teachers": [[1, ["Teacher_MPass"]]], "rooms": [[1, ["A202"]]], "after": {"EASI501": {"EASI501_TPA1_TP2": {"min_offset": 0}, "EASI501_TPA2_TP2": {"min_offset": 0}, "EASI501_TPB1_TP2": {"min_offset": 0}, "EASI501_TPB2_TP2": {"min_offset": 0}, "EASI501_TPC1_TP2": {"min_offset": 0}, "EASI501_TPC2_TP2": {"min_offset": 0}, "EASI501_TPD1_TP2": {"min_offset": 0}, "EASI501_TPD2_TP2": {"min_offset": 0}, "EASI501_TPE1_TP2": {"min_offset": 0}, "EASI501_TPE2_TP2": {"min_offset": 0}, "EASI501_TPG1_TP2": {"min_offset": 0}, "EASI501_TPG2_TP2": {"min_offset": 0}}}, "students": "TPC2", "min_start_slot": null, "max_start_slot": null}, "EASI501_TPD1_TP3": {"kind": "TP", "duration": 16, "teachers": [[1, ["Teacher_FLep"]]], "rooms": [[1, ["A202"]]], "after": {"EASI501": {"EASI501_TPA1_TP2": {"min_offset": 0}, "EASI501_TPA2_TP2": {"min_offset": 0}, "EASI501_TPB1_TP2": {"min_offset": 0}, "EASI501_TPB2_TP2": {"min_offset": 0}, "EASI501_TPC1_TP2": {"min_offset": 0}, "EASI501_TPC2_TP2": {"min_offset": 0}, "EASI501_TPD1_TP2": {"min_offset": 0}, "EASI501_TPD2_TP2": {"min_offset": 0}, "EASI501_TPE1_TP2": {"min_offset": 0}, "EASI501_TPE2_TP2": {"min_offset": 0}, "EASI501_TPG1_TP2": {"min_offset": 0}, "EASI501_TPG2_TP2": {"min_offset": 0}}}, "students": "TPD1", "min_start_slot": null, "max_start_slot": null}, "EASI501_TPD2_TP3": {"kind": "TP", "duration": 16, "teachers": [[1, ["Teacher_MPass"]]], "rooms": [[1, ["A202"]]], "after": {"EASI501": {"EASI501_TPA1_TP2": {"min_offset": 0}, "EASI501_TPA2_TP2": {"min_offset": 0}, "EASI501_TPB1_TP2": {"min_offset": 0}, "EASI501_TPB2_TP2": {"min_offset": 0}, "EASI501_TPC1_TP2": {"min_offset": 0}, "EASI501_TPC2_TP2": {"min_offset": 0}, "EASI501_TPD1_TP2": {"min_offset": 0}, "EASI501_TPD2_TP2": {"min_offset": 0}, "EASI501_TPE1_TP2": {"min_offset": 0}, "EASI501_TPE2_TP2": {"min_offset": 0}, "EASI501_TPG1_TP2": {"min_offset": 0}, "EASI501_TPG2_TP2": {"min_offset": 0}}}, "students": "TPD2", "min_start_slot": null, "max_start_slot": null}, "EASI501_TPE1_TP3": {"kind": "TP", "duration": 16, "teachers": [[1, ["Teacher_MPass"]]], "rooms": [[1, ["A202"]]], "after": {"EASI501": {"EASI501_TPA1_TP2": {"min_offset": 0}, "EASI501_TPA2_TP2": {"min_offset": 0}, "EASI501_TPB1_TP2": {"min_offset": 0}, "EASI501_TPB2_TP2": {"min_offset": 0}, "EASI501_TPC1_TP2": {"min_offset": 0}, "EASI501_TPC2_TP2": {"min_offset": 0}, "EASI501_TPD1_TP2": {"min_offset": 0}, "EASI501_TPD2_TP2": {"min_offset": 0}, "EASI501_TPE1_TP2": {"min_offset": 0}, "EASI501_TPE2_TP2": {"min_offset": 0}, "EASI501_TPG1_TP2": {"min_offset": 0}, "EASI501_TPG2_TP2": {"min_offset": 0}}}, "students": "TPE1", "min_start_slot": null, "max_start_slot": null}, "EASI501_TPE2_TP3": {"kind": "TP", "duration": 16, "teachers": [[1, ["Teacher_FLep"]]], "rooms": [[1, ["A202"]]], "after": {"EASI501": {"EASI501_TPA1_TP2": {"min_offset": 0}, "EASI501_TPA2_TP2": {"min_offset": 0}, "EASI501_TPB1_TP2": {"min_offset": 0}, "EASI501_TPB2_TP2": {"min_offset": 0}, "EASI501_TPC1_TP2": {"min_offset": 0}, "EASI501_TPC2_TP2": {"min_offset": 0}, "EASI501_TPD1_TP2": {"min_offset": 0}, "EASI501_TPD2_TP2": {"min_offset": 0}, "EASI501_TPE1_TP2": {"min_offset": 0}, "EASI501_TPE2_TP2": {"min_offset": 0}, "EASI501_TPG1_TP2": {"min_offset": 0}, "EASI501_TPG2_TP2": {"min_offset": 0}}}, "students": "TPE2", "min_start_slot": null, "max_start_slot": null}, "EASI501_TPG1_TP3": {"kind": "TP", "duration": 16, "teachers": [[1, ["Teacher_FLep"]]], "rooms": [[1, ["A202"]]], "after": {"EASI501": {"EASI501_TPA1_TP2": {"min_offset": 0}, "EASI501_TPA2_TP2": {"min_offset": 0}, "EASI501_TPB1_TP2": {"min_offset": 0}, "EASI501_TPB2_TP2": {"min_offset": 0}, "EASI501_TPC1_TP2": {"min_offset": 0}, "EASI501_TPC2_TP2": {"min_offset": 0}, "EASI501_TPD1_TP2": {"min_offset": 0}, "EASI501_TPD2_TP2": {"min_offset": 0}, "EASI501_TPE1_TP2": {"min_offset": 0}, "EASI501_TPE2_TP2": {"min_offset": 0}, "EASI501_TPG1_TP2": {"min_offset": 0}, "EASI501_TPG2_TP2": {"min_offset": 0}}}, "students": "TPG1", "min_start_slot": null, "max_start_slot": null}, "EASI501_TPG2_TP3": {"kind": "TP", "duration": 16, "teachers": [[1, ["Teacher_FLep"]]], "rooms": [[1, ["A202"]]], "after": {"EASI501": {"EASI501_TPA1_TP2": {"min_offset": 0}, "EASI501_TPA2_TP2": {"min_offset": 0}, "EASI501_TPB1_TP2": {"min_offset": 0}, "EASI501_TPB2_TP2": {"min_offset": 0}, "EASI501_TPC1_TP2": {"min_offset": 0}, "EASI501_TPC2_TP2": {"min_offset": 0}, "EASI501_TPD1_TP2": {"min_offset": 0}, "EASI501_TPD2_TP2": {"min_offset": 0}, "EASI501_TPE1_TP2": {"min_offset": 0}, "EASI501_TPE2_TP2": {"min_offset": 0}, "EASI501_TPG1_TP2": {"min_offset": 0}, "EASI501_TPG2_TP2": {"min_offset": 0}}}, "students": "TPG2", "min_start_slot": null, "max_start_slot": null}, "EASI501_CM_TC_CC2": {"kind": "EX", "duration": 1, "teachers": [[1, ["Teacher_Flep"]]], "rooms": [[2, ["Room_amphi_1", "Room_amphi_2"]]], "after": {"EASI501": {"EASI501_TDA_TD6": {"min_offset": 0}, "EASI501_TDB_TD6": {"min_offset": 0}, "EASI501_TDC_TD6": {"min_offset": 0}, "EASI501_TDD_TD6": {"min_offset": 0}, "EASI501_TDE_TD6": {"min_offset": 0}, "EASI501_TDG_TD6": {"min_offset": 0}, "EASI501_TPA1_TP3": {"min_offset": 0}, "EASI501_TPA2_TP3": {"min_offset": 0}, "EASI501_TPB1_TP3": {"min_offset": 0}, "EASI501_TPB2_TP3": {"min_offset": 0}, "EASI501_TPC1_TP3": {"min_offset": 0}, "EASI501_TPC2_TP3": {"min_offset": 0}, "EASI501_TPD1_TP3": {"min_offset": 0}, "EASI501_TPD2_TP3": {"min_offset": 0}, "EASI501_TPE1_TP3": {"min_offset": 0}, "EASI501_TPE2_TP3": {"min_offset": 0}, "EASI501_TPG1_TP3": {"min_offset": 0}, "EASI501_TPG2_TP3": {"min_offset": 0}}}, "students": "CM_TC", "min_start_slot": null, "max_start_slot": null}}}}
